pysparklib/__init__.py
pysparklib/exceptions.py
pysparklib/ml/__init__.py
pysparklib/pmml/__init__.py
pysparklib-0.0.8.dist-info/LICENSE
pysparklib-0.0.8.dist-info/METADATA
pysparklib-0.0.8.dist-info/WHEEL
pysparklib-0.0.8.dist-info/top_level.txt
pysparklib-0.0.8.dist-info/RECORD
