Metadata-Version: 2.1
Name: pysparklib
Version: 0.0.8
Summary: A elaborate and developed PySpark libraries and resources.
Home-page: https://github.com/deyoulee/pysparklib
Author: Deyou Lee
Author-email: deyoulee@126.com
License: MIT License
Requires-Dist: py4j (==0.10.7)
Requires-Dist: pyspark (==2.4.0)
Requires-Dist: pyspark-stubs (==2.4.0.post2)
Requires-Dist: pyspark2pmml (==0.5.1)
